pip_setting/__init__.py
pip_setting/mirrors.json
pip_setting-1.0.2.dist-info/LICENSE
pip_setting-1.0.2.dist-info/METADATA
pip_setting-1.0.2.dist-info/WHEEL
pip_setting-1.0.2.dist-info/entry_points.txt
pip_setting-1.0.2.dist-info/top_level.txt
pip_setting-1.0.2.dist-info/RECORD
