Metadata-Version: 2.1
Name: pip-setting
Version: 1.0.2
Summary: 快速设置pip镜像源的工具
Home-page: https://github.com/qq1u/pip_setting
Author: Hugh
Author-email: 609799548@qq.com
License: MIT Licence
Classifier: Programming Language :: Python :: 3
Classifier: License :: OSI Approved :: MIT License
Classifier: Operating System :: OS Independent
License-File: LICENSE
